cqls/__init__.py
cqls/expand_quantifiers.py
cqls/interpreter.py
cqls/lexer.py
cqls/nodes.py
cqls/parser.py
cqls/tokens.py
cqls/values.py
cqls-0.1.6.dist-info/METADATA
cqls-0.1.6.dist-info/WHEEL
cqls-0.1.6.dist-info/top_level.txt
cqls-0.1.6.dist-info/RECORD
