Metadata-Version: 2.1
Name: cqls
Version: 0.1.6
Summary: A parser for an often-used subset of Corpus Query Language
Home-page: http://github.com/liao961120/cqls
Author: Yongfu Liao
Author-email: liao961120@github.com
License: MIT
Platform: UNKNOWN
